blazekit/__init__.py
blazekit/__main__.py
blazekit-1.0.2.dist-info/METADATA
blazekit-1.0.2.dist-info/WHEEL
blazekit-1.0.2.dist-info/top_level.txt
blazekit-1.0.2.dist-info/RECORD
