Metadata-Version: 2.1
Name: blazekit
Version: 1.0.2
Summary: UI to interact with Kubernetes Clusters
Home-page: UNKNOWN
Author: Rishabh Jain
Author-email: rishabhking05@gmail.com
License: UNKNOWN
Project-URL: Source Code, https://github.com/rishabhjain05/BlazeKit
Keywords: python,kubernetes,aws cli
Platform: UNKNOWN
Requires-Dist: bleach (==6.0.0)
Requires-Dist: certifi (==2023.5.7)
Requires-Dist: charset-normalizer (==3.1.0)
Requires-Dist: docutils (==0.20.1)
Requires-Dist: idna (==3.4)
Requires-Dist: importlib-metadata (==6.6.0)
Requires-Dist: importlib-resources (==5.12.0)
Requires-Dist: jaraco.classes (==3.2.3)
Requires-Dist: keyring (==23.13.1)
Requires-Dist: markdown-it-py (==2.2.0)
Requires-Dist: mdurl (==0.1.2)
Requires-Dist: more-itertools (==9.1.0)
Requires-Dist: pkginfo (==1.9.6)
Requires-Dist: Pygments (==2.15.1)
Requires-Dist: readme-renderer (==37.3)
Requires-Dist: requests (==2.30.0)
Requires-Dist: requests-toolbelt (==1.0.0)
Requires-Dist: rfc3986 (==2.0.0)
Requires-Dist: rich (==13.3.5)
Requires-Dist: six (==1.16.0)
Requires-Dist: twine (==4.0.2)
Requires-Dist: typing-extensions (==4.5.0)
Requires-Dist: urllib3 (==2.0.2)
Requires-Dist: webencodings (==0.5.1)
Requires-Dist: zipp (==3.15.0)
